quakesaver_client/__init__.py
quakesaver_client/client_websocket.py
quakesaver_client/errors.py
quakesaver_client/fdsnws.py
quakesaver_client/models/__init__.py
quakesaver_client/models/cloud_sensor.py
quakesaver_client/models/data_product_query.py
quakesaver_client/models/data_products.py
quakesaver_client/models/local_sensor.py
quakesaver_client/models/measurement.py
quakesaver_client/models/permission.py
quakesaver_client/models/sensor_state.py
quakesaver_client/models/token.py
quakesaver_client/models/warnings.py
quakesaver_client/models/websocket.py
quakesaver_client/types.py
quakesaver_client/util.py
quakesaver_client-1.2.0.dist-info/LICENSE
quakesaver_client-1.2.0.dist-info/METADATA
quakesaver_client-1.2.0.dist-info/WHEEL
quakesaver_client-1.2.0.dist-info/RECORD
