Metadata-Version: 2.1
Name: quakesaver-client
Version: 1.2.0
Summary: Client library for interacting with the QuakeSaver sensor fleet.
Home-page: https://quakesaver.net/
License: BSD-3-Clause
Author: QuakeSaver
Author-email: info@quakesaver.net
Requires-Python: >=3.9,<3.12
Classifier: License :: OSI Approved :: BSD License
Classifier: Programming Language :: Python :: 3
Classifier: Programming Language :: Python :: 3.9
Classifier: Programming Language :: Python :: 3.10
Classifier: Programming Language :: Python :: 3.11
Requires-Dist: aiohttp (>=3.8.4,<4.0.0)
Requires-Dist: pydantic (>=1.10.5,<1.11.0)
Requires-Dist: requests (>=2.28.2,<2.29.0)
Project-URL: Documentation, https://quakesaver.github.io/quakesaver-client/
Project-URL: Repository, https://github.com/QuakeSaver/quakesaver-client
